{
  "the day after tomorrow": "next 2 days",
  "next 2 days": "next 2 days",
  "next two days": "next 2 days",
  "current": "today",
  "today": "today",
  "curent": "today",
  "next day": "tomorrow",
  "tomorrow": "tomorrow",
  "temp": "temperature",
  "temperature": "temperature",
  "humid": "humidity",
  "humidity": "humidity",
  "hanoi": "Hanoi",
  "next 2 day": "next 2 days",
  "next two day": "next 2 days",
  "in the next two days": "next 2 days",
  "within the next 48 hours": "next 2 days",
  "upcoming 48 hours": "next 2 days",
  "upcoming two days": "next 2 days",
  "the following 2 days": "next 2 days",
  "within the next couple of days": "next 2 days",
  "upcoming days": "next 2 days",
  "the 2 days ahead": "next 2 days",
  "the subsequent 48 hours": "next 2 days",
  "the upcoming two days": "next 2 days",
  "next couple of days": "next 2 days",
  "the 2 days to come": "next 2 days",
  "the following two days": "next 2 days",
  "the next 48 hours": "next 2 days",
  "within the next pair of days": "next 2 days",
  "currently": "current",
  "now": "current",
  "todayss": "current",
  "ttodays": "current",
  "at the moment": "current",
  "present": "current",
  "in the present time": "current",
  "presently": "current",
  "in this moment": "current",
  "at this time": "current",
  "right now": "current",
  "in the current time": "current",
  "as of now": "current",
  "these days": "current",
  "in the here and now": "current",
  "at present": "current",
  "in the now": "current",
  "at the current time": "current",
  "for today": "current",
  "later": "today",
  "later today": "today",
  "going to": "today",
  "this day": "today",
  "this date": "today",
  "on this day": "today",
  "this very day": "today",
  "during the day": "today",
  "in the course of today": "today",
  "within today": "today",
  "throughout the day": "today",
  "on this date": "today",
  "on this very day": "today",
  "during this day": "today",
  "this particular day": "today",
  "within the day": "today",
  "all day": "today",
  "tommorow": "tomorrow",
  "tomorow": "tomorrow",
  "next 24 hours": "tomorrow",
  "on the morrow": "tomorrow",
  "in the coming day": "tomorrow",
  "the succeeding day": "tomorrow",
  "next calendar day": "tomorrow",
  "the subsequent day": "tomorrow",
  "the upcoming day": "tomorrow",
  "within a day": "tomorrow",
  "degree": "temperature",
  "weather": "temperature",
  "climate": "temperature",
  "atmospheric temperature": "temperature",
  "heat level": "temperature",
  "thermal condition": "temperature",
  "thermometer reading": "temperature",
  "ambient temperature": "temperature",
  "warmth": "temperature",
  "coldness": "temperature",
  "hotness": "temperature",
  "fahrenheit": "temperature",
  "celsius": "temperature",
  "kelvin": "temperature",
  "heat index": "temperature",
  "chill factor": "temperature",
  "mercury level": "temperature",
  "weather conditions": "temperature",
  "temp reading": "temperature",
  "moisture level": "humidity",
  "dampness": "humidity",
  "wetness": "humidity",
  "mugginess": "humidity",
  "dewiness": "humidity",
  "water content": "humidity",
  "humidity level": "humidity",
  "atmospheric moisture": "humidity",
  "wet atmosphere": "humidity",
  "damp conditions": "humidity",
  "wet air": "humidity",
  "moisture content": "humidity",
  "moisture in the air": "humidity",
  "moistness": "humidity",
  "relative humidity": "humidity",
  "air dampness": "humidity",
  "wet climate": "humidity",
  "damp air": "humidity",
  "humid conditions": "humidity",
  "level of humidity": "humidity",
  "wind": "wind",
  "rain": "rain",
  "sunny": "sunny",
  "storm": "storm",
  "snow": "snow",
  "when": "when",
  "liverpool": "Liverpool",
  "paris": "Paris",
  "new york city": "New York City",
  "tokyo": "Tokyo",
  "beijing": "Beijing",
  "sydney": "Sydney",
  "cairo": "Cairo",
  "rio de janeiro": "Rio de Janeiro",
  "dubai": "Dubai",
  "barcelona": "Barcelona",
  "cape town": "Cape Town",
  "los angeles": "Los Angeles",
  "moscow": "Moscow",
  "berlin": "Berlin",
  "rome": "Rome",
  "marrakech": "Marrakech",
  "singapore": "Singapore",
  "toronto": "Toronto",
  "istanbul": "Istanbul",
  "buenos aires": "Buenos Aires",
  "milan": "Milan",
  "london": "London",
  "mumbai": "mumbai",
  "delhi": "delhi",
  "bangalore": "bangalore",
  "hyderbad": "hyderbad",
  "trivanduram": "trivanduram",
  "chennai": "chennai",
  "ho chi minh city": "Ho Chi Minh City",
  "danang": "Danang",
  "viet tri": "Viet Tri",
  "phu tho": "Phu Tho",
  "thanh hoa": "Thanh Hoa",
  "kolkata": "kolkata",
  "thiruvandrum": "thiruvandrum"
}